odoo/addons/l10n_it_pos_fiscalcode/README.rst
odoo/addons/l10n_it_pos_fiscalcode/__init__.py
odoo/addons/l10n_it_pos_fiscalcode/__manifest__.py
odoo/addons/l10n_it_pos_fiscalcode/i18n/it.po
odoo/addons/l10n_it_pos_fiscalcode/i18n/l10n_it_pos_fiscalcode.pot
odoo/addons/l10n_it_pos_fiscalcode/readme/CONTRIBUTORS.rst
odoo/addons/l10n_it_pos_fiscalcode/readme/DESCRIPTION.rst
odoo/addons/l10n_it_pos_fiscalcode/static/description/icon.png
odoo/addons/l10n_it_pos_fiscalcode/static/description/index.html
odoo/addons/l10n_it_pos_fiscalcode/static/src/js/models.js
odoo/addons/l10n_it_pos_fiscalcode/static/src/xml/pos.xml
odoo/addons/l10n_it_pos_fiscalcode/views/assets.xml
odoo12_addon_l10n_it_pos_fiscalcode-12.0.1.0.1.dist-info/METADATA
odoo12_addon_l10n_it_pos_fiscalcode-12.0.1.0.1.dist-info/WHEEL
odoo12_addon_l10n_it_pos_fiscalcode-12.0.1.0.1.dist-info/top_level.txt
odoo12_addon_l10n_it_pos_fiscalcode-12.0.1.0.1.dist-info/RECORD
